README.md
setup.cfg
setup.py
bibsearch/__init__.py
bibsearch/bibdb.py
bibsearch/bibsearch.py
bibsearch/bibutils.py
bibsearch/config.py
bibsearch/manual.1
bibsearch.egg-info/PKG-INFO
bibsearch.egg-info/SOURCES.txt
bibsearch.egg-info/dependency_links.txt
bibsearch.egg-info/entry_points.txt
bibsearch.egg-info/requires.txt
bibsearch.egg-info/top_level.txt