Metadata-Version: 1.2
Name: bibsearch
Version: 0.3.9
Summary: Download, manage, and search a BibTeX database.
Home-page: https://github.com/mjpost/bibsearch
Author: David Vilar, Matt Post
Author-email: david.vilar@gmail.com, post@cs.jhu.edu
License: Apache License 2.0
Keywords: computer science, LaTeX, BibTeX
Platform: UNKNOWN
Classifier: Development Status :: 5 - Production/Stable
Classifier: Intended Audience :: Developers
Classifier: Intended Audience :: Science/Research
Classifier: Topic :: Scientific/Engineering
Classifier: Topic :: Text Processing
Classifier: License :: OSI Approved :: Apache Software License
Classifier: Programming Language :: Python :: 3 :: Only
Requires-Python: >=3
